Workbook

Sheet README
A1: Storitvene in projektne dejavnosti Strukturirani raziskovalni registri
A4: Različica | B4: 1.0
A5: Datum raziskave | B5: 2026-08-07
A6: Primarni trg | B6: Slovenija
A7: Primarni ICP | B7: B2B storitvena in projektna podjetja z 20-500 zaposlenimi
A8: Namen | B8: Stabilni ID-ji za kalkulator, RAG, diagnostični vprašalnik, ICP scoring in priporočilni engine.
A9: Pomembno | B9: Benchmarki so orientacijske referenčne točke, ne avtomatske ciljne vrednosti.
A10: Uporaba | B10: Filtrirajte registre po ID-jih; benchmark vedno preverite glede vzorca, leta, geografije in definicije.

Sheet Market
A1: id | B1: SKD/NACE | C1: Podjetja | D1: Zaposleni in samozaposleni | E1: Neto promet (mio EUR) | F1: Dodana vrednost (mio EUR) | G1: Dodana vrednost na osebo (EUR)
A2: MKT-001 | B2: J Informacijske in komunikacijske dejavnosti | C2: 12870 | D2: 36721 | E2: 5492 | F2: 2408 | G2: =F2*1000000/D2 -> 65575.556
A3: MKT-002 | B3: M Strokovne, znanstvene in tehnične dejavnosti | C3: 41792 | D3: 71913 | E3: 7542 | F3: 3199 | G3: =F3*1000000/D3 -> 44484.307
A4: MKT-003 | B4: N Druge raznovrstne poslovne dejavnosti | C4: 10827 | D4: 37743 | E4: 2625 | F4: 1189 | G4: =F4*1000000/D4 -> 31502.53
A5: MKT-004 | B5: Skupaj J+M+N | C5: 65489 | D5: 146377 | E5: 15659 | F5: 6796 | G5: =F5*1000000/D5 -> 46428.059

Sheet Archetypes
A1: id | B1: Arhetip | C1: Jedrna ekonomika | D1: Največji problemi | E1: Najboljši Datalab vstop | F1: ID
A2: ARC-01 | B2: Svetovalno podjetje | C2: ure, fiksni projekt, retainer | D2: utilization, scope creep, realizacija | E2: finance, čas, projektni stroški, DMS; PSA partner | F2: ARC-01
A3: ARC-02 | B3: Kreativna/marketinška agencija | C3: retainer in projekti | D3: over-servicing, rework, nejasna marža | E3: čas, stroški, periodični računi, BI; CRM/PM integracija | F3: ARC-02
A4: ARC-03 | B4: Arhitektura/projektiranje | C4: projekt, faza, mejnik | D4: napačna ocena, spremembe, WIP | E4: stroškovna mesta/projekti, DMS, potni stroški, računi | F4: ARC-03
A5: ARC-04 | B5: Inženiring | C5: projekt + material + podizvajalci | D5: nabava, field data, stroški, EAC | E5: finance, nabava, skladišče, servis, DMS | F5: ARC-04
A6: ARC-05 | B6: IT razvoj | C6: čas/material ali fiksni sprint/projekt | D6: bench, spremembe, rework, obračun | E6: čas, stroški, ponavljajoči računi; PSA/ALM integracija | F6: ARC-05
A7: ARC-06 | B7: Sistemski integrator | C7: projekt + licence/oprema + podpora | D7: več tokov marže, podizvajalci, renewal | E7: prodaja/nabava, zaloga, projektna analitika, periodični obračun | F7: ARC-06
A8: ARC-07 | B8: MSP/managed services | C8: mesečna pogodba + projekti | D8: ticket cost, presežene ure, SLA, churn | E8: pogodbe/računi/terjatve; ITSM/PSA integracija | F8: ARC-07
A9: ARC-08 | B9: Terenski servis | C9: poseg + čas + pot + material | D9: dispečiranje, FTFR, papir, zamuda računa | E9: Granula Servis na terenu | F9: ARC-08
A10: ARC-09 | B10: Montažno-tehnični izvajalec | C10: fiksni projekt + material | D10: plan, material, prevzem, podizvajalci | E10: delovni/servisni nalogi, skladišče, potni nalogi, DMS | F10: ARC-09
A11: ARC-10 | B11: Staffing/body leasing | C11: potrjene ure x tarifa | D11: neodobrene ure, bench, plača-tarifa | E11: čas, kadri, plače, pogodbe, račun | F11: ARC-10
A12: ARC-11 | B12: Facility/outsourced services | C12: lokacija, pogodba, SLA | D12: razporedi, prisotnost, kakovost, penal | E12: kadri, čas, stroški, periodični računi; FSM partner | F12: ARC-11
A13: ARC-12 | B13: Izobraževanja/dogodki | C13: dogodek, udeleženec, paket | D13: kapaciteta, odpovedi, stroški dogodka | E13: finance, dokumenti, obveščanje; booking/CRM integracija | F13: ARC-12

Sheet Personas
A1: id | B1: Persona | C1: Primarni cilj | D1: Kaj jo boli | E1: Kaj potrebuje od sistema | F1: Nakupna vloga
A2: PER-001 | B2: Lastnik/direktor | C2: rast in denar brez izgube nadzora | D2: »promet raste, denarja in marže pa ne vidim« | E2: enoten pogled, zgodnji alarmi | F2: odločevalec/sponzor
A3: PER-002 | B3: COO/vodja izvedbe | C3: zanesljiva izvedba | D3: stalno preplaniranje in eskalacije | E3: portfelj, kapaciteta, odgovornosti | F3: sponzor
A4: PER-003 | B4: CFO/finance | C4: marža, račun, denar, skladnost | D4: pozni in sporni računi, neznan WIP | E4: finance, projektni P&L, DSO | F4: ekonomski kupec
A5: PER-004 | B5: Prodaja/BD | C5: hitre in konkurenčne ponudbe | D5: čakanje na ocene, izgubljen kontekst | E5: CRM/CPQ in pravila cen | F5: vplivnež
A6: PER-005 | B6: Estimator/presales | C6: realna ocena | D6: slabi zgodovinski podatki | E6: predloge, stroški, pretekla realizacija | F6: uporabnik
A7: PER-006 | B7: PMO | C7: standard in portfelj | D7: različne metode in statusi | E7: standardni projekti, stage gates | F7: lastnik procesa
A8: PER-007 | B8: Projektni vodja | C8: rok, obseg, proračun | D8: ure in stroški pridejo prepozno | E8: budget-actual-EAC, change log | F8: ključni uporabnik
A9: PER-008 | B9: Resource manager | C9: prava oseba ob pravem času | D9: nepregledne kapacitete in znanja | E9: razpoložljivost, skills, forecast | F9: ključni uporabnik
A10: PER-009 | B10: Vodja servisa | C10: SLA, kakovost, produktivnost | D10: napačen tehnik/material, ponovni obiski | E10: dispatch, asset history, FTFR | F10: sponzor/uporabnik
A11: PER-010 | B11: Dispečer | C11: izvedljiv dnevni plan | D11: telefonsko usklajevanje | E11: lokacije, urniki, prioritete | F11: uporabnik
A12: PER-011 | B12: Izvajalec/tehnik | C12: čim manj administracije | D12: dvojni vnos in nejasna navodila | E12: mobilni vnos, dokumenti, offline | F12: uporabnik/možen blokator
... A16: PER-015 | B16: IT | C16: stabilnost, varnost, integracije | D16: razdrobljen stack in shadow IT | E16: arhitektura, API, avtorizacije | F16: vratar

Sheet Processes
A1: id | B1: Proces | C1: Minimalni podatki | D1: Ključni KPI | E1: Tipična napaka | F1: ID
A2: PROC-01 | B2: segmentacija in kvalifikacija | C2: stranka, potreba, fit, verjetnost | D2: qualified win rate | E2: prodaja neustreznega posla | F2: PROC-01
A3: PROC-02 | B3: ocena obsega | C3: deliverables, predpostavke, WBS, ure, stroški | D3: estimate accuracy | E3: optimistična ocena | F3: PROC-02
A4: PROC-03 | B4: priprava ponudbe | C4: cena, model, roki, izključitve | D4: proposal turnaround | E4: ročno sestavljanje | F4: PROC-03
A5: PROC-04 | B5: pogodba/SLA | C5: obseg, tarifa, mejniki, SLA, dokazila | D5: contract cycle time | E5: manjkajoče komercialne kontrole | F5: PROC-04
A6: PROC-05 | B6: predaja prodaja-izvedba | C6: zaveze, ocena, tveganja, kontakti | D6: handoff completeness | E6: izguba konteksta | F6: PROC-05
A7: PROC-06 | B7: postavitev projekta/naloga | C7: pogodba, WBS, proračun, tarife | D7: setup lead time | E7: projekt brez baselinea | F7: PROC-06
A8: PROC-07 | B8: plan kapacitet | C8: demand, FTE, odsotnosti, skills | D8: forecast accuracy | E8: plan samo po osebah, ne po znanjih | F8: PROC-07
A9: PROC-08 | B9: razporejanje | C9: prioriteta, lokacija, skills, rok | D9: schedule adherence | E9: ročno preplaniranje | F9: PROC-08
A10: PROC-09 | B10: izvedba | C10: naloge, status, dokazi | D10: on-time delivery | E10: status po občutku | F10: PROC-09
A11: PROC-10 | B11: časovnice | C11: oseba, projekt, naloga, billable flag | D11: on-time timesheets | E11: tedenska rekonstrukcija | F11: PROC-10
A12: PROC-11 | B12: stroški in poti | C12: projekt, kategorija, dokazilo | D12: expense capture rate | E12: račun brez projekta | F12: PROC-11
... A30: PROC-29 | B30: analiza storitvene baze | C30: asset, pogodba, stroški, prihodki | D30: margin per contract/asset | E30: dobičkonosnost ni vidna | F30: PROC-29

Sheet ICP_Scoring
A1: id | B1: Dimenzija | C1: Teža | D1: Primer signalov
A2: ICP-001 | B2: Osnovni fit | C2: 15 | D2: SKD, B2B, 20-500 zaposlenih
A3: ICP-002 | B3: Procesna kompleksnost | C3: 15 | D3: projekti, lokacije, SLA, material, podizvajalci
A4: ICP-003 | B4: Finančni potencial | C4: 15 | D4: prihodki, rast, stroški dela, več entitet
A5: ICP-004 | B5: Intenzivnost bolečine | C5: 15 | D5: pozni računi, zaposlovanje administracije, maržni pritisk
A6: ICP-005 | B6: Trigger/timing | C6: 10 | D6: nova lokacija, CFO/PMO, razpis, M&A, e-računi
A7: ICP-006 | B7: PANTHEON fit | C7: 15 | D7: finance, kadri, servis, skladišče, dokumenti
A8: ICP-007 | B8: Podatkovna pripravljenost | C8: 5 | D8: javno omenjeno ERP/CRM/ISO, standardni procesi
A9: ICP-008 | B9: Dostop/kanal | C9: 5 | D9: Datalab partner, računovodski servis, dogodek
A10: ICP-009 | B10: Spremembna pripravljenost | C10: 5 | D10: digitalne investicije, vodstvena pobuda

Sheet Pain_Groups
A1: id | B1: Double-count skupina | C1: Bolečina | D1: Primarni finančni učinek | E1: Ne seštevaj avtomatsko z
A2: PAIN-001 | B2: DC-01 Capacity | C2: iskanje podatkov, dvojni vnos, ročna poročila | D2: vrednost administrativne kapacitete | E2: istimi urami po več modulih
A3: PAIN-002 | B3: DC-02 Utilization | C3: bench, čakanje, slabo razporejanje | D3: izgubljena prispevna marža ali odložena zaposlitev | E3: polno prodajno vrednostjo vseh ur
A4: PAIN-003 | B4: DC-03 Scope | C4: neodobrene spremembe in over-servicing | D4: erozija marže/povrnjen prihodek | E4: rework urami, če so iste
A5: PAIN-004 | B5: DC-04 Quality | C5: napake, reklamacije, ponovni obisk | D5: neposredni strošek + kapaciteta | E5: scope creep, če je vzrok zahteva stranke
A6: PAIN-005 | B6: DC-05 Billing | C6: manjkajoče ure, napačne tarife, ročni račun | D6: povrnjena marža + administracija | E6: WIP sprostitvijo kot letni prihodek
A7: PAIN-006 | B7: DC-06 Working capital | C7: WIP, DSO, spori | D7: enkratna sprostitev kapitala + financiranje | E7: polnim zneskom kot letni prihranek
A8: PAIN-007 | B8: DC-07 Field | C8: pot, ponovni obisk, napačen material | D8: vozilo, čas, material, SLA | E8: kakovostjo, če je isti ponovni obisk
A9: PAIN-008 | B9: DC-08 Contracts | C9: presežene ure, manjkajoča indeksacija, churn | D9: marža pogodbe in retencija | E9: splošnim billing leakage
A10: PAIN-009 | B10: DC-09 External spend | C10: podizvajalci, urgentna nabava, nadure | D10: neposredni denarni odtok | E10: polnim stroškom rednih zaposlenih
A11: PAIN-010 | B11: DC-10 Risk | C11: skladnost, varnost, odvisnost od ključnih ljudi | D11: pričakovana vrednost tveganja | E11: navideznim 100% prihrankom

Sheet KPIs
A1: id | B1: KPI | C1: Formula | D1: Uporaba | E1: Previdnost
A2: KPI-001 | B2: Proposal turnaround | C2: datum oddaje - datum kvalificirane zahteve | D2: hitrost prodaje | E2: loči kompleksnost ponudbe
A3: KPI-002 | B3: Win rate | C3: dobljene / odločene ponudbe | D3: prodajna kakovost | E3: ne vključuj še odprtih
A4: KPI-003 | B4: Estimate accuracy | C4: (dejansko - ocena) / ocena | D4: kakovost ocene | E4: loči ure in strošek
A5: KPI-004 | B5: Backlog coverage | C5: potrjeni backlog / mesečna izvedbena kapaciteta | D5: prihodnja zasedenost | E5: pogodbeni, ne pipeline
A6: KPI-005 | B6: Billable utilization | C6: zaračunljive ure / dogovorjene razpoložljive ure | D6: monetizacija kapacitete | E6: vedno navedi imenovalec
A7: KPI-006 | B7: Realization | C7: realizirani prihodek / standardna vrednost dela | D7: cenovna in obračunska disciplina | E7: ni utilization
A8: KPI-007 | B8: Realized rate | C8: storitveni prihodek / zaračunane ure | D8: dejanska cena ure | E8: segmentiraj po vlogi
A9: KPI-008 | B9: Project gross margin | C9: (prihodek - neposredni stroški) / prihodek | D9: ekonomika projekta | E9: konsistentna alokacija dela
A10: KPI-009 | B10: Forecast margin variance | C10: dejanska marža - napovedana marža | D10: kakovost EAC | E10: primerjaj isto časovno točko
A11: KPI-010 | B11: On-time delivery | C11: pravočasno zaključeni / zaključeni | D11: izvedbena zanesljivost | E11: dogovor o spremembah roka
A12: KPI-011 | B12: Change capture | C12: odobrena vrednost sprememb / identificirana upravičena vrednost | D12: zaščita obsega | E12: zahteva change log
... A21: KPI-020 | B21: FTFR | C21: prvič rešeni terenski nalogi / vsi zaključeni | D21: terenska kakovost | E21: jasno definiraj ponovni obisk

Sheet Benchmarks
A1: id | B1: Benchmark | C1: Vrednost | D1: Vzorec/obdobje | E1: Uporaba
A2: BM-001 | B2: Billable utilization | C2: 68,9% | D2: 403 globalnih PSO, poslovanje 2024 | E2: alarm, ne cilj za vse segmente
A3: BM-002 | B3: On-time delivery | C3: 73,4% | D3: isti vir | E3: primerjava projektne discipline
A4: BM-003 | B4: EBITDA marža | C4: 9,8% | D4: isti vir | E4: okolje pritiska na marže
A5: BM-004 | B5: Projektna marža | C5: 37,7% | D5: isti vir | E5: orientacija, definicija preveriti
A6: BM-005 | B6: PSA učinek | C6: +8% utilization, +11% projektna marža, +117% EBITDA | D6: korelacijski ponudniški povzetek | E6: ne uporabljati kot ROI predpostavko
A7: BM-006 | B7: A&E operating profit/net revenue | C7: 21,4% | D7: skoraj 900 severnoameriških A&E podjetij, 2024 | E7: samo za A&E primerjavo
A8: BM-007 | B8: A&E projekti na/pod proračunom | C8: 75% | D8: isti vir | E8: projektna disciplina
A9: BM-008 | B9: FTFR median | C9: 71,9% | D9: Aquant 2024, več industrij | E9: terenski alarmni pas
A10: BM-009 | B10: Nepotrebni truck rolls | C10: 14% | D10: Aquant 2025 | E10: diagnostično vprašanje
A11: BM-010 | B11: Zamudne B2B prodaje na kredit v Sloveniji | C11: 38% | D11: Atradius 2025 | E11: kontekst terjatev
A12: BM-011 | B12: Podjetja z ERP v Sloveniji | C12: 35% | D12: SURS 2025, podjetja 10+ | E12: zrelost trga
A13: BM-012 | B13: Podjetja s CRM v Sloveniji | C13: 21% | D13: SURS 2025, podjetja 10+ | E13: integracijska vrzel
A15: Benchmarki so orientacijski alarmni pragovi. Pred uporabo preverite definicijo, segment, geografijo, leto in vzorec; korelacij ne obravnavajte kot kavzalni ROI.

Sheet PANTHEON
A1: id | B1: Potrebna zmožnost | C1: PANTHEON dokaz | D1: Pokritost | E1: Opomba
A2: CAP-001 | B2: računovodstvo in finance | C2: glavna knjiga, saldakonti, avtomatsko knjiženje | D2: standardna | E2: močan temelj
A3: CAP-002 | B3: prihodki/stroški po dimenzijah | C3: stroškovna mesta, oddelki, analize | D3: standardna/delna | E3: potrditi globino projektnega P&L
A4: CAP-003 | B4: izdani in prejeti računi | C4: prodaja, nabava, DDV | D4: standardna | E4: neposreden fit
A5: CAP-004 | B5: terjatve in plačila | C5: odprte postavke, bančne povezave | D5: standardna | E5: neposreden fit
A6: CAP-005 | B6: ponavljajoči računi | C6: javno navedena funkcija | D6: standardna | E6: potrditi pogodbeno avtomatiko in indeksacije
A7: CAP-006 | B7: kadri, odsotnosti, plače | C7: HERA/kadri/plače | D7: standardna | E7: lokalizacija je prednost
A8: CAP-007 | B8: evidenca delovnega časa | C8: kadri/granule | D8: standardna | E8: ločiti prisotnost od projektnih časovnic
A9: CAP-008 | B9: potni nalogi in stroški | C9: mobilna granula | D9: standardna | E9: foto dokazila, kilometrina, dnevnice
A10: CAP-009 | B10: DMS in dokumentni workflow | C10: DMS, Workflow, eDokumentacija | D10: standardna/dodatna storitev | E10: dobra dokazna sled
A11: CAP-010 | B11: e-računi/OCR | C11: eIzmenjava, eKnjižbe | D11: dodatna storitev | E11: relevantno za 2028 B2B mandat
A12: CAP-011 | B12: BI in dashboardi | C12: ZEUS in nadzorne plošče | D12: odvisno od licence | E12: močna finančna analitika
... A17: CAP-016 | B17: CRM | C17: partnerske rešitve | D17: partnerska | E17: jedro nima polnega CRM

Sheet Questions
A1: id | B1: module | C1: persona | D1: question | E1: evidence_requested | F1: related_metric
A2: Q-001 | B2: Arhetip | C2: Direktor | D2: Kolikšen delež prihodkov pri modelu »Svetovalno podjetje« prihaja iz vsakega pogodbenega modela? | E2: Prihodki zadnjih 12 mesecev po pogodbi in modelu
A3: Q-002 | B3: Arhetip | C3: CFO | D3: Ali za »Svetovalno podjetje« vidite prispevno maržo pred koncem meseca? | E3: Primer zadnjega mesečnega poročila | F3: Project gross margin
A4: Q-003 | B4: Arhetip | C4: Direktor | D4: Kolikšen delež prihodkov pri modelu »Kreativna/marketinška agencija« prihaja iz vsakega pogodbenega modela? | E4: Prihodki zadnjih 12 mesecev po pogodbi in modelu
A5: Q-004 | B5: Arhetip | C5: CFO | D5: Ali za »Kreativna/marketinška agencija« vidite prispevno maržo pred koncem meseca? | E5: Primer zadnjega mesečnega poročila | F5: Project gross margin
A6: Q-005 | B6: Arhetip | C6: Direktor | D6: Kolikšen delež prihodkov pri modelu »Arhitektura/projektiranje« prihaja iz vsakega pogodbenega modela? | E6: Prihodki zadnjih 12 mesecev po pogodbi in modelu
A7: Q-006 | B7: Arhetip | C7: CFO | D7: Ali za »Arhitektura/projektiranje« vidite prispevno maržo pred koncem meseca? | E7: Primer zadnjega mesečnega poročila | F7: Project gross margin
A8: Q-007 | B8: Arhetip | C8: Direktor | D8: Kolikšen delež prihodkov pri modelu »Inženiring« prihaja iz vsakega pogodbenega modela? | E8: Prihodki zadnjih 12 mesecev po pogodbi in modelu
A9: Q-008 | B9: Arhetip | C9: CFO | D9: Ali za »Inženiring« vidite prispevno maržo pred koncem meseca? | E9: Primer zadnjega mesečnega poročila | F9: Project gross margin
A10: Q-009 | B10: Arhetip | C10: Direktor | D10: Kolikšen delež prihodkov pri modelu »IT razvoj« prihaja iz vsakega pogodbenega modela? | E10: Prihodki zadnjih 12 mesecev po pogodbi in modelu
A11: Q-010 | B11: Arhetip | C11: CFO | D11: Ali za »IT razvoj« vidite prispevno maržo pred koncem meseca? | E11: Primer zadnjega mesečnega poročila | F11: Project gross margin
A12: Q-011 | B12: Arhetip | C12: Direktor | D12: Kolikšen delež prihodkov pri modelu »Sistemski integrator« prihaja iz vsakega pogodbenega modela? | E12: Prihodki zadnjih 12 mesecev po pogodbi in modelu
A13: Q-012 | B13: Arhetip | C13: CFO | D13: Ali za »Sistemski integrator« vidite prispevno maržo pred koncem meseca? | E13: Primer zadnjega mesečnega poročila | F13: Project gross margin
A14: Q-013 | B14: Arhetip | C14: Direktor | D14: Kolikšen delež prihodkov pri modelu »MSP/managed services« prihaja iz vsakega pogodbenega modela? | E14: Prihodki zadnjih 12 mesecev po pogodbi in modelu
A15: Q-014 | B15: Arhetip | C15: CFO | D15: Ali za »MSP/managed services« vidite prispevno maržo pred koncem meseca? | E15: Primer zadnjega mesečnega poročila | F15: Project gross margin
A16: Q-015 | B16: Arhetip | C16: Direktor | D16: Kolikšen delež prihodkov pri modelu »Terenski servis« prihaja iz vsakega pogodbenega modela? | E16: Prihodki zadnjih 12 mesecev po pogodbi in modelu
A17: Q-016 | B17: Arhetip | C17: CFO | D17: Ali za »Terenski servis« vidite prispevno maržo pred koncem meseca? | E17: Primer zadnjega mesečnega poročila | F17: Project gross margin
A18: Q-017 | B18: Arhetip | C18: Direktor | D18: Kolikšen delež prihodkov pri modelu »Montažno-tehnični izvajalec« prihaja iz vsakega pogodbenega modela? | E18: Prihodki zadnjih 12 mesecev po pogodbi in modelu
A19: Q-018 | B19: Arhetip | C19: CFO | D19: Ali za »Montažno-tehnični izvajalec« vidite prispevno maržo pred koncem meseca? | E19: Primer zadnjega mesečnega poročila | F19: Project gross margin
A20: Q-019 | B20: Arhetip | C20: Direktor | D20: Kolikšen delež prihodkov pri modelu »Staffing/body leasing« prihaja iz vsakega pogodbenega modela? | E20: Prihodki zadnjih 12 mesecev po pogodbi in modelu
A21: Q-020 | B21: Arhetip | C21: CFO | D21: Ali za »Staffing/body leasing« vidite prispevno maržo pred koncem meseca? | E21: Primer zadnjega mesečnega poročila | F21: Project gross margin
A22: Q-021 | B22: Arhetip | C22: Direktor | D22: Kolikšen delež prihodkov pri modelu »Facility/outsourced services« prihaja iz vsakega pogodbenega modela? | E22: Prihodki zadnjih 12 mesecev po pogodbi in modelu
A23: Q-022 | B23: Arhetip | C23: CFO | D23: Ali za »Facility/outsourced services« vidite prispevno maržo pred koncem meseca? | E23: Primer zadnjega mesečnega poročila | F23: Project gross margin
A24: Q-023 | B24: Arhetip | C24: Direktor | D24: Kolikšen delež prihodkov pri modelu »Izobraževanja/dogodki« prihaja iz vsakega pogodbenega modela? | E24: Prihodki zadnjih 12 mesecev po pogodbi in modelu
A25: Q-024 | B25: Arhetip | C25: CFO | D25: Ali za »Izobraževanja/dogodki« vidite prispevno maržo pred koncem meseca? | E25: Primer zadnjega mesečnega poročila | F25: Project gross margin
A26: Q-025 | B26: Proces | C26: Lastnik procesa | D26: Pokažite zadnji konkreten primer procesa »segmentacija in kvalifikacija«. Kje je nastalo največ čakanja ali ponovnega vnosa? | E26: Časovni žig, dokument in odgovorna oseba | F26: qualified win rate
A27: Q-026 | B27: Proces | C27: Lastnik procesa | D27: Pokažite zadnji konkreten primer procesa »ocena obsega«. Kje je nastalo največ čakanja ali ponovnega vnosa? | E27: Časovni žig, dokument in odgovorna oseba | F27: estimate accuracy
A28: Q-027 | B28: Proces | C28: Lastnik procesa | D28: Pokažite zadnji konkreten primer procesa »priprava ponudbe«. Kje je nastalo največ čakanja ali ponovnega vnosa? | E28: Časovni žig, dokument in odgovorna oseba | F28: proposal turnaround
A29: Q-028 | B29: Proces | C29: Lastnik procesa | D29: Pokažite zadnji konkreten primer procesa »pogodba/SLA«. Kje je nastalo največ čakanja ali ponovnega vnosa? | E29: Časovni žig, dokument in odgovorna oseba | F29: contract cycle time
A30: Q-029 | B30: Proces | C30: Lastnik procesa | D30: Pokažite zadnji konkreten primer procesa »predaja prodaja-izvedba«. Kje je nastalo največ čakanja ali ponovnega vnosa? | E30: Časovni žig, dokument in odgovorna oseba | F30: handoff completeness
A31: Q-030 | B31: Proces | C31: Lastnik procesa | D31: Pokažite zadnji konkreten primer procesa »postavitev projekta/naloga«. Kje je nastalo največ čakanja ali ponovnega vnosa? | E31: Časovni žig, dokument in odgovorna oseba | F31: setup lead time
A32: Q-031 | B32: Proces | C32: Lastnik procesa | D32: Pokažite zadnji konkreten primer procesa »plan kapacitet«. Kje je nastalo največ čakanja ali ponovnega vnosa? | E32: Časovni žig, dokument in odgovorna oseba | F32: forecast accuracy
A33: Q-032 | B33: Proces | C33: Lastnik procesa | D33: Pokažite zadnji konkreten primer procesa »razporejanje«. Kje je nastalo največ čakanja ali ponovnega vnosa? | E33: Časovni žig, dokument in odgovorna oseba | F33: schedule adherence
A34: Q-033 | B34: Proces | C34: Lastnik procesa | D34: Pokažite zadnji konkreten primer procesa »izvedba«. Kje je nastalo največ čakanja ali ponovnega vnosa? | E34: Časovni žig, dokument in odgovorna oseba | F34: on-time delivery
A35: Q-034 | B35: Proces | C35: Lastnik procesa | D35: Pokažite zadnji konkreten primer procesa »časovnice«. Kje je nastalo največ čakanja ali ponovnega vnosa? | E35: Časovni žig, dokument in odgovorna oseba | F35: on-time timesheets
A36: Q-035 | B36: Proces | C36: Lastnik procesa | D36: Pokažite zadnji konkreten primer procesa »stroški in poti«. Kje je nastalo največ čakanja ali ponovnega vnosa? | E36: Časovni žig, dokument in odgovorna oseba | F36: expense capture rate
... A74: Q-073 | B74: KPI | C74: CFO/COO | D74: Kako danes definirate in merite »FTFR« ter katera odločitev sledi odstopanju? | E74: Formula, lastnik, vir, 12-mesečni trend | F74: FTFR

Sheet Maturity
A1: id | B1: Raven | C1: Opis | D1: dimension
A2: MAT-001 | B2: 0 Nevidno | C2: proces ni definiran; rezultat je odvisen od posameznika
A3: MAT-002 | B3: 1 Ročno | C3: e-pošta, papir in lokalni Excel; podatki so reaktivni
A4: MAT-003 | B4: 2 Osnovno digitalno | C4: posamezna orodja obstajajo, povezave in standardi so šibki
A5: MAT-004 | B5: 3 Povezano | C5: skupni ID-ji, standardni workflowi in redni KPI-ji
A6: MAT-005 | B6: 4 Vodeno | C6: napovedi, izjeme, lastniki podatkov in merjenje koristi
A7: MAT-006 | B7: 5 Prilagodljivo | C7: skoraj realni čas, prediktivni signali in stalna optimizacija
A8: MDIM-01 | D8: CRM in prodaja
A9: MDIM-02 | D9: Ponudbe in pogodbe
A10: MDIM-03 | D10: Projekti
A11: MDIM-04 | D11: Planiranje virov
A12: MDIM-05 | D12: Čas in stroški
A13: MDIM-06 | D13: Obračun
A14: MDIM-07 | D14: WIP in terjatve
A15: MDIM-08 | D15: Dokumenti
A16: MDIM-09 | D16: Analitika
A17: MDIM-10 | D17: Integracije
A18: MDIM-11 | D18: Servis in SLA
A19: MDIM-12 | D19: Terensko delo
... A21: MDIM-14 | D21: Uporabniška disciplina

Sheet TCO
A1: id | B1: Kategorija | C1: Enkratno | D1: Tekoče | E1: Pogosto pozabljeno
A2: TCO-001 | B2: Licence/naročnine | C2: lahko | D2: da | E2: granularni uporabniki, konektorji, storage
A3: TCO-002 | B3: Implementacija | C3: da | D3: spremembe | E3: procesni design, testiranje
A4: TCO-003 | B4: Migracija | C4: da | D4: občasno | E4: čiščenje šifrantov in odprtih postavk
A5: TCO-004 | B5: Integracije | C5: da | D5: da | E5: monitoring in spremembe API-jev
A6: TCO-005 | B6: Prilagoditve | C6: da | D6: da | E6: regresijsko testiranje
A7: TCO-006 | B7: Izobraževanje | C7: da | D7: osveževanje | E7: novi zaposleni in vodje
A8: TCO-007 | B8: Notranji čas | C8: da | D8: da | E8: product owner, super users, UAT
A9: TCO-008 | B9: Padec produktivnosti | C9: da | D9: ne | E9: dvojno vodenje v prehodu
A10: TCO-009 | B10: Podpora/gostovanje | C10: ne | D10: da | E10: odzivni nivo in partner
A11: TCO-010 | B11: Ukinjene rešitve | C11: negativni strošek | D11: negativni strošek | E11: pogodbeni odpovedni roki

Sheet Sources
A1: id | B1: name | C1: url
A2: SRC-001 | B2: SURS, strukturna poslovna statistika 2024 | C2: https://www.stat.si/StatWeb/en/News/Index/14354
A3: SRC-002 | B3: SURS, Digitalno podjetništvo 2025 | C3: https://www.stat.si/StatWeb/en/news/Index/14010
A4: SRC-003 | B4: SPI/Kantata 2025 | C4: https://get.kantata.com/rs/677-LEJ-696/images/2025-ps-maturity-benchmark.pdf
A5: SRC-004 | B5: Atradius, Slovenija 2025 | C5: https://atradius.co.nz/dam/jcr%3Acd9ecbf4-a2f5-463e-ab5f-740b53c458b9/payment-practices-barometer-central-and-eastern-europe-2025-slovenia-en.pdf
A6: SRC-005 | B6: Datalab, Servis na terenu | C6: https://www.datalab.si/pantheon-granule/granula-servis-na-terenu/
A7: SRC-006 | B7: SURS, podrobni podatki ICT in velikostni razredi | C7: https://www.stat.si/StatWeb/en/News/Index/14466
A8: SRC-007 | B8: SURS, ICT sektor 2024 | C8: https://www.stat.si/StatWeb/en/News/Index/13854
A9: SRC-008 | B9: Aquant 2025 | C9: https://discover.aquant.ai/service-benchmark-report
A10: SRC-009 | B10: GOV.SI, zagotavljanje dela delavcev uporabniku | C10: https://www.gov.si/teme/zagotavljanje-dela-delavcev-uporabniku/
A11: SRC-010 | B11: Deltek Clarity 2025 | C11: https://www.deltek.com/company/news/what-the-46th-annual-deltek-clarity-ae-study-reveals-about-the-industry/
A12: SRC-011 | B12: SAP, PSA | C12: https://www.sap.com/resources/what-is-psa-software
... A37: SRC-036 | B37: Datalab - Licenčne cene in konektorji | C37: https://www.datalab.eu/pantheon-license-prices/

Sheet Open_Gaps
A1: id | B1: gap | C1: status
A2: GAP-01 | B2: Opportunity-to-project in poln CRM | C2: zahteva interno potrditev
A3: GAP-02 | B3: CPQ in strukturirano ocenjevanje ponudbe | C3: zahteva interno potrditev
A4: GAP-03 | B4: Skill-based resource planning in scenariji | C4: zahteva interno potrditev
A5: GAP-04 | B5: Projektni baseline ter ETC/EAC po vlogah | C5: zahteva interno potrditev
A6: GAP-05 | B6: Formalni change-order register | C6: zahteva interno potrditev
A7: GAP-06 | B7: Napredno milestone/WIP/revenue recognition | C7: zahteva interno potrditev
A8: GAP-07 | B8: Vključene ure, SLA časovniki in renewal workflow | C8: zahteva interno potrditev
A9: GAP-08 | B9: ITSM/ticketing | C9: zahteva interno potrditev
A10: GAP-09 | B10: Dinamično dispatchiranje in optimizacija poti | C10: zahteva interno potrditev
A11: GAP-10 | B11: Offline terenska uporaba v vseh scenarijih | C11: zahteva interno potrditev
A12: GAP-11 | B12: Večentitetna projektna profitabilnost | C12: zahteva interno potrditev
A13: GAP-12 | B13: Javno dokumentirani API endpointi in omejitve | C13: zahteva interno potrditev

Sheet Checks
A1: Register | B1: Expected rows | C1: Workbook rows | D1: Status
A2: Market | B2: 4 | C2: =COUNTA(Market!A2:A5) -> 4 | D2: =IF(B2=C2,"OK","CHECK") -> OK
A3: Archetypes | B3: 12 | C3: =COUNTA(Archetypes!A2:A13) -> 12 | D3: =IF(B3=C3,"OK","CHECK") -> OK
A4: Personas | B4: 15 | C4: =COUNTA(Personas!A2:A16) -> 15 | D4: =IF(B4=C4,"OK","CHECK") -> OK
A5: Processes | B5: 29 | C5: =COUNTA(Processes!A2:A30) -> 29 | D5: =IF(B5=C5,"OK","CHECK") -> OK
A6: Pain_Groups | B6: 10 | C6: =COUNTA(Pain_Groups!A2:A11) -> 10 | D6: =IF(B6=C6,"OK","CHECK") -> OK
A7: KPIs | B7: 20 | C7: =COUNTA(KPIs!A2:A21) -> 20 | D7: =IF(B7=C7,"OK","CHECK") -> OK
A8: Benchmarks | B8: 12 | C8: =COUNTA(Benchmarks!A2:A13) -> 12 | D8: =IF(B8=C8,"OK","CHECK") -> OK
A9: PANTHEON | B9: 16 | C9: =COUNTA(PANTHEON!A2:A17) -> 16 | D9: =IF(B9=C9,"OK","CHECK") -> OK
A10: ICP_Scoring | B10: 9 | C10: =COUNTA(ICP_Scoring!A2:A10) -> 9 | D10: =IF(B10=C10,"OK","CHECK") -> OK
A11: Questions | B11: 73 | C11: =COUNTA(Questions!A2:A74) -> 73 | D11: =IF(B11=C11,"OK","CHECK") -> OK
A12: Maturity | B12: 20 | C12: =COUNTA(Maturity!A2:A21) -> 20 | D12: =IF(B12=C12,"OK","CHECK") -> OK
A13: TCO | B13: 10 | C13: =COUNTA(TCO!A2:A11) -> 10 | D13: =IF(B13=C13,"OK","CHECK") -> OK
A14: Sources | B14: 36 | C14: =COUNTA(Sources!A2:A37) -> 36 | D14: =IF(B14=C14,"OK","CHECK") -> OK
A15: Open_Gaps | B15: 12 | C15: =COUNTA(Open_Gaps!A2:A13) -> 12 | D15: =IF(B15=C15,"OK","CHECK") -> OK
